setup.py
melugd_probability/Binomialdistribution.py
melugd_probability/Gaussiandistribution.py
melugd_probability/Generaldistribution.py
melugd_probability/__init__.py
melugd_probability.egg-info/PKG-INFO
melugd_probability.egg-info/SOURCES.txt
melugd_probability.egg-info/dependency_links.txt
melugd_probability.egg-info/not-zip-safe
melugd_probability.egg-info/top_level.txt