Metadata-Version: 1.0
Name: melugd-probability
Version: 1.0
Summary: Gaussian and Binomial distributions
Home-page: UNKNOWN
Author: Meljohn Ugaddan
Author-email: UNKNOWN
License: UNKNOWN
Platform: UNKNOWN
